amino/__init__.py
amino/acm.py
amino/client.py
amino/socket.py
amino/sub_client.py
amino/lib/__init__.py
amino/lib/util/__init__.py
amino/lib/util/device.py
amino/lib/util/exceptions.py
amino/lib/util/headers.py
amino/lib/util/helpers.py
amino/lib/util/objects.py
amino/lib/util/voice_header.py
kyo-1.1.2.dist-info/LICENSE
kyo-1.1.2.dist-info/METADATA
kyo-1.1.2.dist-info/WHEEL
kyo-1.1.2.dist-info/top_level.txt
kyo-1.1.2.dist-info/RECORD
