Metadata-Version: 2.1
Name: kyo
Version: 1.1.2
Summary: Library for the creation of bots from the AminoApps platform.
Home-page: https://github.com/Sstandby/kyo
Download-URL: https://github.com/Sstandby/kyo/tarball/master
Author: Sstandby
Author-email: standby@sstandby.com
License: MIT
Keywords: aminoapps,kyo,amino,aminokyo,aminobots,amino-bot,narvii,api,python,python3,python3.x,sstandby,standby,official
License-File: LICENSE
Requires-Dist: setuptools
Requires-Dist: requests
Requires-Dist: six
Requires-Dist: websockets
Requires-Dist: json-minify
Requires-Dist: websocket-client (==1.3.1)
Requires-Dist: aiohttp
